{
  "cli": {
    "version": ">= 3.17.0"
  },
  "build": {
    "preview": {
      "distribution": "internal",
      "android": {
        "buildType": "apk"
      },
      "env": {
        "EXPO_PUBLIC_API_URL": "https://checklist-api.smartnewservices.com.br"
      }
    },
    "production": {
      "distribution": "store",
      "env": {
        "EXPO_PUBLIC_API_URL": "https://checklist-api.smartnewservices.com.br"
      },
      "android": {
        "buildType": "app-bundle"
      }
    }
  },
  "submit": {
    "production": {
      
    }
  }
}